chainflow/__init__.py
chainflow-0.0.0.dist-info/METADATA
chainflow-0.0.0.dist-info/WHEEL
chainflow-0.0.0.dist-info/RECORD
