Metadata-Version: 2.1
Name: chainflow
Version: 0.0.0
Summary: Fluent data pipelines with method chaining
Author-email: iyanging <iyanging@163.com>
Requires-Python: >=3.12
